rabbit_in_a_blender-0.0.74.dist-info/licenses/LICENSE
riab/__init__.py
riab/cli.py
riab/assets/dqd.css
riab/etl/achilles.py
riab/etl/cdm_5.4_events.json
riab/etl/cleanup.py
riab/etl/create_cdm_folders.py
riab/etl/create_omop_db.py
riab/etl/data_quality.py
riab/etl/data_quality_dashboard.py
riab/etl/db.py
riab/etl/etl.py
riab/etl/etl_base.py
riab/etl/import_vocabularies.py
riab/etl/sql_render_base.py
riab/etl/utils.py
riab/etl/bigquery/achilles.py
riab/etl/bigquery/cleanup.py
riab/etl/bigquery/create_cdm_folders.py
riab/etl/bigquery/create_omop_db.py
riab/etl/bigquery/data_quality.py
riab/etl/bigquery/data_quality_dashboard.py
riab/etl/bigquery/etl.py
riab/etl/bigquery/etl_base.py
riab/etl/bigquery/gcp.py
riab/etl/bigquery/import_vocabularies.py
riab/etl/bigquery/templates/cdm_folders/sample_etl_query.sql.jinja
riab/etl/bigquery/templates/cdm_folders/sample_usagi_query.sql.jinja
riab/etl/bigquery/templates/cleanup/CONCEPT_remove_custom_concepts.sql.jinja
riab/etl/bigquery/templates/cleanup/CONCEPT_remove_custom_concepts_by_{omop_table}__{concept_id_column}_usagi_table.sql.jinja
riab/etl/bigquery/templates/cleanup/SOURCE_ID_TO_OMOP_ID_MAP_remove_ids_by_omop_table.sql.jinja
riab/etl/bigquery/templates/cleanup/SOURCE_TO_CONCEPT_MAP_remove_concepts_by_{omop_table}__{concept_id_column}_usagi_table.sql.jinja
riab/etl/bigquery/templates/cleanup/all_work_table_names.sql.jinja
riab/etl/bigquery/templates/cleanup/truncate.sql.jinja
riab/etl/bigquery/templates/ddl/DataQualityDashboard_ddl.sql.jinja
riab/etl/bigquery/templates/ddl/OMOPCDM_bigquery_5.4_clustering_fields.json
riab/etl/bigquery/templates/ddl/OMOPCDM_bigquery_5.4_ddl.sql.jinja
riab/etl/bigquery/templates/ddl/SOURCE_ID_TO_OMOP_ID_MAP_ddl.sql.jinja
riab/etl/bigquery/templates/ddl/result_table_ddl_concept.sql.jinja
riab/etl/bigquery/templates/ddl/result_table_ddl_field.sql.jinja
riab/etl/bigquery/templates/ddl/result_table_ddl_table.sql.jinja
riab/etl/bigquery/templates/dqd/get_dqd_run.sql.jinja
riab/etl/bigquery/templates/dqd/get_dqd_run_results.sql.jinja
rabbit_in_a_blender-0.0.74.dist-info/METADATA
rabbit_in_a_blender-0.0.74.dist-info/WHEEL
rabbit_in_a_blender-0.0.74.dist-info/entry_points.txt
rabbit_in_a_blender-0.0.74.dist-info/top_level.txt
rabbit_in_a_blender-0.0.74.dist-info/RECORD
