Metadata-Version: 2.4
Name: Rabbit-in-a-Blender
Version: 0.0.74
Summary: An ETL pipeline to transform your EMP data to OMOP.
Author-email: Lammertyn Pieter-Jan <pieter-jan.lammertyn@azdelta.be>, De Jaeger Peter <peter.dejaeger@azdelta.be>
License:                     GNU GENERAL PUBLIC LICENSE
Project-URL: Homepage, https://radar-azdelta.github.io/Rabbit-in-a-Blender/
Project-URL: Source Code, https://github.com/RADar-AZDelta/Rabbit-in-a-Blender
Project-URL: Bug Tracker, https://github.com/RADar-AZDelta/Rabbit-in-a-Blender/issues
Keywords: OMOP,CDM,common data model,OHDSI
Classifier: Programming Language :: Python :: 3
Classifier: License :: OSI Approved :: GNU General Public License v3 or later (GPLv3+)
Classifier: Operating System :: OS Independent
Requires-Python: >=3.10
License-File: LICENSE
Requires-Dist: backoff>=2.2.1
Requires-Dist: polars>=1.0.0
Requires-Dist: jinja2>=3.1.4
Requires-Dist: pyarrow>=16.1.0
Requires-Dist: google-cloud-bigquery>=3.25.0
Requires-Dist: google-cloud-storage>=2.17.0
Requires-Dist: google-auth>=2.31.0
Requires-Dist: humanfriendly>=10.0
Requires-Dist: jpype1>=1.5.0
Requires-Dist: dash>=2.17.1
Requires-Dist: dash-table>=5.0.0
Requires-Dist: dash-bootstrap-components>=1.6.0
Requires-Dist: pymssql>=2.3.0
Requires-Dist: python-dotenv>=1.0.1
Requires-Dist: sqlalchemy>=2.0.31
Requires-Dist: pywin32>=306; platform_system == "Windows"
Requires-Dist: sqlparse>=0.5.0
Dynamic: license-file
